SQUARNA/1000.conf
SQUARNA/1000nobpp.conf
SQUARNA/500.conf
SQUARNA/500nobpp.conf
SQUARNA/LICENSE
SQUARNA/README.md
SQUARNA/SQRNalgos.py
SQUARNA/SQRNdbnali.py
SQUARNA/SQRNdbnseq.py
SQUARNA/SQUARNA.py
SQUARNA/__init__.py
SQUARNA/ali.conf
SQUARNA/alt.conf
SQUARNA/def.conf
SQUARNA/edmonds.conf
SQUARNA/edmondsnobpp.conf
SQUARNA/fastest.conf
SQUARNA/greedy.conf
SQUARNA/greedynobpp.conf
SQUARNA/hungarian.conf
SQUARNA/hungariannobpp.conf
SQUARNA/nobpp.conf
SQUARNA/nussinov.conf
SQUARNA/nussinovnobpp.conf
SQUARNA/requirements.txt
SQUARNA/datasets/SRtest150.fas
SQUARNA/datasets/SRtrain150.fas
SQUARNA/examples/ali_input.afa
SQUARNA/examples/demo.afa
SQUARNA/examples/seq_input.fas
SQUARNA/examples/shape_input.fas
squarna-2.3.dist-info/METADATA
squarna-2.3.dist-info/WHEEL
squarna-2.3.dist-info/entry_points.txt
squarna-2.3.dist-info/licenses/LICENSE
squarna-2.3.dist-info/RECORD
