Metadata-Version: 2.4
Name: SQUARNA
Version: 2.3
Summary: SQUARNA tool for RNA secondary structure prediction
Project-URL: Homepage, https://github.com/febos/SQUARNA
Project-URL: Issues, https://github.com/febos/SQUARNA/issues
Author-email: "Eugene F. Baulin" <efbaulin@gmail.com>
Maintainer-email: "Eugene F. Baulin" <efbaulin@gmail.com>
License-File: LICENSE
Classifier: Operating System :: OS Independent
Classifier: Programming Language :: Python :: 3
Classifier: Topic :: Scientific/Engineering :: Bio-Informatics
Requires-Python: >=3.8
Requires-Dist: networkx
Requires-Dist: numpy
Requires-Dist: scipy
Requires-Dist: viennarna
